semideep/__init__.py
semideep/experiment.py
semideep/loss.py
semideep/trainer.py
semideep/utils.py
semideep/weight_computer.py
semideep-0.0.1.dist-info/METADATA
semideep-0.0.1.dist-info/WHEEL
semideep-0.0.1.dist-info/top_level.txt
semideep-0.0.1.dist-info/RECORD
