Metadata-Version: 2.4
Name: semideep
Version: 0.0.1
Summary: Distance-based weighting for semi-supervised deep learning
Home-page: https://github.com/aydin/semideep
Author: Aydin Abedinia
Author-email: abedinia.aydin@gmail.com
Classifier: Programming Language :: Python :: 3
Classifier: License :: OSI Approved :: MIT License
Classifier: Operating System :: OS Independent
Classifier: Topic :: Scientific/Engineering :: Artificial Intelligence
Requires-Python: >=3.7
Requires-Dist: numpy>=1.19.0
Requires-Dist: torch>=1.7.0
Requires-Dist: scikit-learn>=0.24.0
Requires-Dist: pandas>=1.1.0
Requires-Dist: matplotlib>=3.3.0
Requires-Dist: seaborn>=0.11.0
Requires-Dist: tqdm>=4.50.0
Dynamic: author
Dynamic: author-email
Dynamic: classifier
Dynamic: description
Dynamic: description-content-type
Dynamic: home-page
Dynamic: requires-dist
Dynamic: requires-python
Dynamic: summary
